Workbook

Sheet Company Tracker
A1: Company | B1: Website | C1: Industry / Sector | D1: Industry Emphasized | E1: NAICS Code | F1: NAICS Code Type | G1: Why This NAICS Code | H1: HQ Location / Footprint | I1: Company Size | J1: Revenue Band / Latest Revenue | K1: Growth / Revenue Signal | L1: Hiring Signal | M1: Recent Hiring Trends | N1: Opportunity Relevance | O1: Opportunity Fit | P1: Category | Q1: Why This Fits | R1: Executive Role Fit | S1: Warm Introduction Path | T1: Outreach Approach | U1: Key Contacts / Priority Titles | V1: Compensation Benchmark | W1: Suggested Search Keywords | X1: Suggested Job Title Keywords | Y1: Source URL | Z1: Priority Score | AA1: Suggested Priority Rank (1-25) | AB1: Status | AC1: Next Action | AD1: Date Researched | AE1: Ownership Type | AF1: Recent M&A Activity | AG1: Signals | AH1: Estimated Deal Size Fit | AI1: M&A Role Fit
A2: Dragos, Inc. | B2: https://www.dragos.com | C2: Cybersecurity Software | D2: OT/ICS threat detection and asset visibility platform for critical infrastructure (electric, oil & gas, manufacturing, water) | E2: 5415 | F2: Primary | G2: Core business is OT/ICS cybersecurity software and services -- Computer Systems Design and Related Services | H2: Hanover, MD (Baltimore-Washington DC area); global -- offices in North America, EMEA, APAC | I2: 500-1,000 employees (sources vary 500-670 as of mid-2026) | J2: ~$154M ARR (2024 estimate, third-party data) | K2: High | L2: Medium-High | M2: Not verified in this pass -- check LinkedIn Jobs/Indeed/dragos.com/careers for current postings | N2: High | O2: High | P2: Actively Expanding / M&A Integration | Q2: Recent acquisitions of NetRise and RunZero (2026) create a natural need for unified brand messaging across newly combined product lines | R2: CMO / VP Marketing | S2: Industry conference circuit (S4, SANS ICS Summit) given CEO Robert M. Lee's high visibility in the ICS security community | T2: Direct outreach referencing recent acquisition announcements as a timely marketing-support angle | U2: CEO & Founder: Robert M. Lee (public). CMO/VP Marketing title not independently verified in this pass. | V2: N/A -- privately held, no 10-K/proxy filings | W2: Dragos marketing, Dragos brand, Dragos communications | X2: VP Marketing, Director of Communications, Head of Brand | Y2: https://pitchbook.com/profiles/company/120194-29 | AA2: =ROUND((_xlfn.SWITCH(TRIM(O2),"Very High",5,"High",4,"Medium-High",3.5,"Medium",3,"Low-Medium",2,"Low",1,3)*2)+(_xlfn.SWITCH(TRIM(N2),"Very High",5,"High",4,"Medium-High",3.5,"Medium",3,"Low-Medium",2,"Low",1,3)*2)+((_xlfn.SWITCH(TRIM(K2),"Very High",5,"High",4,"Medium-High",3.5,"Medium",3,"Low-Medium",2,"Low",1,3)+_xlfn.SWITCH(TRIM(L2),"Very High",5,"High",4,"Medium-High",3.5,"Medium",3,"Low-Medium",2,"Low",1,3)+3)/3),1) -> 19.5 | AD2: July 24, 2026 | AE2: Privately held; 2026 trade press reported a possible Accenture majority-stake investment (not independently confirmed here) | AF2: Acquired NetRise and RunZero (2026) | AG2: Active acquirer of point solutions; integrating multiple recent acquisitions | AH2: N/A -- no confirmed evidence Dragos itself is currently for sale | AI2: Likely Acquirer
A3: Claroty Ltd. | B3: https://claroty.com | C3: Cybersecurity Software | D3: Cyber-physical systems (CPS) protection platform spanning OT, IoMT (healthcare), and IoT | E3: 5415 | F3: Primary | G3: Core business is CPS/OT cybersecurity software -- Computer Systems Design and Related Services | H3: New York, NY; ~350 employees in Israel, remainder across US/Europe/APAC/LatAm | I3: 500-1,000 employees (sources vary 500-850 as of mid-2026) | J3: Not fully disclosed; $3B valuation as of Jan 2026 Series F | K3: Very High | L3: High | M3: Not verified in this pass -- check LinkedIn Jobs/Indeed/claroty.com/careers for current postings | N3: High | O3: Very High | P3: Actively Expanding / Recently Funded | Q3: Fresh $150M Series F (Jan 2026) at a $3B valuation, plus new Gartner Magic Quadrant Leader recognition, create an ideal window for amplified brand/PR marketing support | R3: CMO / VP Marketing | S3: Investor network (Golub Growth, Bessemer Venture Partners, SoftBank Vision Fund 2) or industry conference circuit | T3: Reference the recent funding round and Gartner recognition as a natural marketing-momentum conversation starter | U3: CEO: Yaniv Vardi (public). Co-founders: Galina Antova, Amir Zilberstein, Benny Porat. | V3: N/A -- privately held, no 10-K/proxy filings | W3: Claroty marketing, Claroty brand, Claroty communications | X3: VP Marketing, Director of Communications, Head of Brand | Y3: https://www.calcalistech.com/ctechnews/article/syuo0xklwe | AA3: =ROUND((_xlfn.SWITCH(TRIM(O3),"Very High",5,"High",4,"Medium-High",3.5,"Medium",3,"Low-Medium",2,"Low",1,3)*2)+(_xlfn.SWITCH(TRIM(N3),"Very High",5,"High",4,"Medium-High",3.5,"Medium",3,"Low-Medium",2,"Low",1,3)*2)+((_xlfn.SWITCH(TRIM(K3),"Very High",5,"High",4,"Medium-High",3.5,"Medium",3,"Low-Medium",2,"Low",1,3)+_xlfn.SWITCH(TRIM(L3),"Very High",5,"High",4,"Medium-High",3.5,"Medium",3,"Low-Medium",2,"Low",1,3)+3)/3),1) -> 22 | AD3: July 24, 2026 | AE3: Privately held, VC-backed (Series F closed Jan 2026) | AF3: None reported as acquisition target; no confirmed recent acquisitions by Claroty in this pass | AG3: Fresh capital raise typically precedes increased marketing/brand investment | AH3: N/A -- not currently signaling M&A activity | AI3: Unclear
A4: Nozomi Networks | B4: https://www.nozominetworks.com | C4: Cybersecurity Software | D4: OT/IoT network monitoring and threat detection for critical infrastructure | E4: 5415 | F4: Primary | G4: Core business is OT/IoT cybersecurity software -- Computer Systems Design and Related Services | H4: San Francisco, CA | I4: ~375-390 employees (pre-acquisition figures, 2026) | J4: ~$63.5M ARR (2025 estimate, third-party data) | K4: High | L4: Medium | M4: Not verified in this pass -- check LinkedIn Jobs/Indeed/nozominetworks.com/careers for current postings | N4: Medium | O4: Medium | P4: Recently Acquired / Integration Phase | Q4: Newly part of Mitsubishi Electric (acquisition announced ~Jan 29, 2026) -- marketing decisions are likely being redefined under new ownership; worth monitoring rather than immediate outreach | R4: CMO (at parent company level, post-integration) | S4: Not clearly identifiable pending integration into Mitsubishi Electric's structure | T4: Monitor for post-acquisition brand/marketing announcements before approaching | U4: Co-Founders: Moreno Carullo (CTO), Andrea Carcano (CPO). CEO name reported inconsistently across sources during 2026 transition -- verify current leadership before outreach. | V4: N/A -- privately held/subsidiary, no 10-K/proxy filings | W4: Nozomi Networks marketing, Nozomi Networks Mitsubishi integration | X4: Marketing Director, Brand Manager | Y4: https://pitchbook.com/profiles/company/167488-48 | AA4: =ROUND((_xlfn.SWITCH(TRIM(O4),"Very High",5,"High",4,"Medium-High",3.5,"Medium",3,"Low-Medium",2,"Low",1,3)*2)+(_xlfn.SWITCH(TRIM(N4),"Very High",5,"High",4,"Medium-High",3.5,"Medium",3,"Low-Medium",2,"Low",1,3)*2)+((_xlfn.SWITCH(TRIM(K4),"Very High",5,"High",4,"Medium-High",3.5,"Medium",3,"Low-Medium",2,"Low",1,3)+_xlfn.SWITCH(TRIM(L4),"Very High",5,"High",4,"Medium-High",3.5,"Medium",3,"Low-Medium",2,"Low",1,3)+3)/3),1) -> 15.3 | AD4: July 24, 2026 | AE4: Subsidiary of Mitsubishi Electric (acquisition announced Jan 29, 2026) | AF4: Acquired by Mitsubishi Electric (Jan 2026) | AG4: Completed strategic acquisition by a major industrial conglomerate | AH4: N/A -- acquisition already completed | AI4: Recently Acquired (Target, completed)
A5: Forescout Technologies, Inc. | B5: https://www.forescout.com | C5: Cybersecurity Software | D5: Agentless network security -- visibility and control for IT, IoT, IoMT, and OT devices | E5: 5415 | F5: Primary | G5: Core business is network/device security software -- Computer Systems Design and Related Services | H5: San Jose, CA; operations in 12 countries including Canada, UK, Netherlands, India, Japan, Singapore, Israel, UAE | I5: ~1,000-1,300 employees (sources vary by date/methodology, 2026) | J5: ~$189M (third-party estimate, 2026) | K5: Medium | L5: Medium | M5: Not verified in this pass -- check LinkedIn Jobs/Indeed/forescout.com/careers for current postings | N5: Medium | O5: Medium | P5: Established / Leadership Refresh | Q5: Mature, PE-backed company; recent CRO promotion and VP Product Marketing hire (Jan 2026) suggest a leadership refresh rather than hypergrowth -- moderate marketing-support opportunity | R5: VP Marketing / Director of Product Marketing | S5: Recently hired/promoted marketing leadership (Rob Amezcua - CRO, Joe Malenfant - VP Product Marketing) may be more open to new vendor conversations during onboarding | T5: Time outreach around the recent executive changes | U5: CEO: Barry Mainz (public). CRO: Rob Amezcua (per Jan 2026 announcement). VP Product Marketing: Joe Malenfant (per Jan 2026 announcement). | V5: N/A -- taken private in 2020 (Advent International / Crosspoint Capital Partners); no current 10-K/proxy filings | W5: Forescout marketing, Forescout brand, Forescout communications | X5: VP Marketing, Director of Product Marketing | Y5: https://leadiq.com/c/forescout/5a1d8b202400002400662666 | AA5: =ROUND((_xlfn.SWITCH(TRIM(O5),"Very High",5,"High",4,"Medium-High",3.5,"Medium",3,"Low-Medium",2,"Low",1,3)*2)+(_xlfn.SWITCH(TRIM(N5),"Very High",5,"High",4,"Medium-High",3.5,"Medium",3,"Low-Medium",2,"Low",1,3)*2)+((_xlfn.SWITCH(TRIM(K5),"Very High",5,"High",4,"Medium-High",3.5,"Medium",3,"Low-Medium",2,"Low",1,3)+_xlfn.SWITCH(TRIM(L5),"Very High",5,"High",4,"Medium-High",3.5,"Medium",3,"Low-Medium",2,"Low",1,3)+3)/3),1) -> 15 | AD5: July 24, 2026 | AE5: Privately held, PE-backed (Advent International and Crosspoint Capital Partners, since 2020) | AF5: None reported since 2020 take-private transaction | AG5: Executive leadership changes (CRO, VP Product Marketing) in Jan 2026 | AH5: N/A -- no current indication of near-term exit activity | AI5: PE-Backed / Possible Future Exit Candidate
A6: Armis, Inc. | B6: https://www.armis.com | C6: Cybersecurity Software | D6: Cyber exposure management platform covering IT, OT, IoT, and medical device assets | E6: 5415 | F6: Primary | G6: Core business is asset intelligence/cyber exposure management software -- Computer Systems Design and Related Services | H6: San Francisco / Palo Alto, CA; ~950 employees globally including a significant Israel presence | I6: ~950 employees (2026, pre-acquisition) | J6: Surpassed $300M ARR in late 2025 (50%+ YoY growth reported) | K6: Very High | L6: High | M6: Not verified in this pass -- check LinkedIn Jobs/Indeed/armis.com/careers for current postings | N6: Medium | O6: Medium | P6: Recently Acquired / Integration Phase | Q6: ServiceNow completed its ~$7.75B acquisition of Armis on April 20, 2026 (per ServiceNow's own 10-Q) -- marketing decisions are now likely being made at the ServiceNow parent-company level | R6: CMO (at ServiceNow parent level, post-integration) | S6: ServiceNow's security/GTM organization, rather than legacy Armis marketing contacts | T6: Monitor for ServiceNow's integration/rebranding announcements before approaching | U6: Co-Founder & CEO (pre-acquisition): Yevgeny Dibrov. Co-Founder & CTO: Nadir Izrael. Post-acquisition reporting lines not yet verified. | V6: N/A -- was privately held; now a wholly owned ServiceNow subsidiary post-acquisition, no separate public filings | W6: Armis marketing, Armis ServiceNow integration | X6: Marketing Director, Brand Manager | Y6: https://www.sec.gov/Archives/edgar/data/0001373715/000137371526000056/now-20260331.htm | AA6: =ROUND((_xlfn.SWITCH(TRIM(O6),"Very High",5,"High",4,"Medium-High",3.5,"Medium",3,"Low-Medium",2,"Low",1,3)*2)+(_xlfn.SWITCH(TRIM(N6),"Very High",5,"High",4,"Medium-High",3.5,"Medium",3,"Low-Medium",2,"Low",1,3)*2)+((_xlfn.SWITCH(TRIM(K6),"Very High",5,"High",4,"Medium-High",3.5,"Medium",3,"Low-Medium",2,"Low",1,3)+_xlfn.SWITCH(TRIM(L6),"Very High",5,"High",4,"Medium-High",3.5,"Medium",3,"Low-Medium",2,"Low",1,3)+3)/3),1) -> 16 | AD6: July 24, 2026 | AE6: Wholly owned subsidiary of ServiceNow, Inc. (NYSE: NOW) -- acquisition closed April 20, 2026 | AF6: Acquired by ServiceNow for ~$7.75B cash (closed April 20, 2026, per ServiceNow Form 10-Q) | AG6: Large strategic acquisition by a public company; funded via $4.0B term loan per ServiceNow's SEC filing | AH6: N/A -- acquisition already completed | AI6: Recently Acquired (Target, completed)

Sheet Job Posting Quick Links
A1: Company | B1: Job Title Used for Search | C1: LinkedIn Jobs Search | D1: Indeed Search | E1: Google Jobs Search
A2: Dragos, Inc. | B2: VP Marketing | C2: =HYPERLINK("https://www.linkedin.com/jobs/search/?keywords="&_xlfn.ENCODEURL(A2)&"%20"&_xlfn.ENCODEURL(B2),"Search LinkedIn") -> Search LinkedIn | D2: =HYPERLINK("https://www.indeed.com/jobs?q="&_xlfn.ENCODEURL(B2)&"+"&_xlfn.ENCODEURL(A2),"Search Indeed") -> Search Indeed | E2: =HYPERLINK("https://www.google.com/search?q="&_xlfn.ENCODEURL(A2)&"+"&_xlfn.ENCODEURL(B2)&"+jobs","Search Google Jobs") -> Search Google Jobs
A3: Claroty Ltd. | B3: VP Marketing | C3: =HYPERLINK("https://www.linkedin.com/jobs/search/?keywords="&_xlfn.ENCODEURL(A3)&"%20"&_xlfn.ENCODEURL(B3),"Search LinkedIn") -> Search LinkedIn | D3: =HYPERLINK("https://www.indeed.com/jobs?q="&_xlfn.ENCODEURL(B3)&"+"&_xlfn.ENCODEURL(A3),"Search Indeed") -> Search Indeed | E3: =HYPERLINK("https://www.google.com/search?q="&_xlfn.ENCODEURL(A3)&"+"&_xlfn.ENCODEURL(B3)&"+jobs","Search Google Jobs") -> Search Google Jobs
A4: Nozomi Networks | B4: Marketing Director | C4: =HYPERLINK("https://www.linkedin.com/jobs/search/?keywords="&_xlfn.ENCODEURL(A4)&"%20"&_xlfn.ENCODEURL(B4),"Search LinkedIn") -> Search LinkedIn | D4: =HYPERLINK("https://www.indeed.com/jobs?q="&_xlfn.ENCODEURL(B4)&"+"&_xlfn.ENCODEURL(A4),"Search Indeed") -> Search Indeed | E4: =HYPERLINK("https://www.google.com/search?q="&_xlfn.ENCODEURL(A4)&"+"&_xlfn.ENCODEURL(B4)&"+jobs","Search Google Jobs") -> Search Google Jobs
A5: Forescout Technologies, Inc. | B5: VP Marketing | C5: =HYPERLINK("https://www.linkedin.com/jobs/search/?keywords="&_xlfn.ENCODEURL(A5)&"%20"&_xlfn.ENCODEURL(B5),"Search LinkedIn") -> Search LinkedIn | D5: =HYPERLINK("https://www.indeed.com/jobs?q="&_xlfn.ENCODEURL(B5)&"+"&_xlfn.ENCODEURL(A5),"Search Indeed") -> Search Indeed | E5: =HYPERLINK("https://www.google.com/search?q="&_xlfn.ENCODEURL(A5)&"+"&_xlfn.ENCODEURL(B5)&"+jobs","Search Google Jobs") -> Search Google Jobs
A6: Armis, Inc. | B6: Marketing Director | C6: =HYPERLINK("https://www.linkedin.com/jobs/search/?keywords="&_xlfn.ENCODEURL(A6)&"%20"&_xlfn.ENCODEURL(B6),"Search LinkedIn") -> Search LinkedIn | D6: =HYPERLINK("https://www.indeed.com/jobs?q="&_xlfn.ENCODEURL(B6)&"+"&_xlfn.ENCODEURL(A6),"Search Indeed") -> Search Indeed | E6: =HYPERLINK("https://www.google.com/search?q="&_xlfn.ENCODEURL(A6)&"+"&_xlfn.ENCODEURL(B6)&"+jobs","Search Google Jobs") -> Search Google Jobs
A8: Important: this tab is a set of pre-built search links, nothing more. Each link opens LinkedIn, Indeed, or Google with the company name and a job title already typed into the search box -- the same as typing them in yourself. Clicking a link does not pull in, list, or embed any actual job postings, and nothing here is "jobs found" -- it's a shortcut to run that search live, whenever you click it.

Sheet Industry Events & Forums
A1: Event Name | B1: Date(s) | C1: Location | D1: Format | E1: Relevant To | F1: URL
A2: S4x27 | B2: February 8-11, 2027 | C2: Tampa, FL | D2: In-person | E2: Actively Expanding / M&A Integration; Actively Expanding / Recently Funded | F2: https://s4xevents.com/
A3: Midwest OT Cybersecurity Summit (MOCS) 2027 | B3: April 16, 2027 | C3: Marquette University, Milwaukee, WI | D3: In-person | E3: All categories -- regional, community-driven OT security event | F3: https://midwest-otcs.org/
A5: Only 2 events are listed here because those are the ones verified via search with a real, working URL and confirmed date at the time this sample was built. A live run of this prompt would search more broadly and may find additional real events -- report fewer events rather than padding the list with unverified ones.

Sheet Company Activity & Events
A1: Company | B1: Recent LinkedIn Activity | C1: Podcast / Webcast Appearances | D1: Upcoming Events / Tradeshows | E1: Source URL(s)
A2: Dragos, Inc. | B2: Jun 23, 2026: "Dragos Launches EmberAI to Address OT Security Skills Gap with AI Assistant" (SiliconAngle) | C2: No recent public activity found | D2: No recent public activity found | E2: https://siliconangle.com (search: Dragos EmberAI)
A3: Claroty Ltd. | B3: Jan 22, 2026: Announced $150M Series F at $3B valuation (PR Newswire). Feb 4, 2026: Claroty xDome recognized by KLAS Research (PR Newswire). | C3: No recent public activity found | D3: No recent public activity found | E3: https://www.claroty.com/newsroom
A4: Nozomi Networks | B4: May 12, 2026: "Nozomi Networks Platform Now Available On Google Cloud Marketplace." Reported joint collaboration announcement with the UAE Cybersecurity Council (~May 2026). | C4: No recent public activity found | D4: No recent public activity found | E4: https://www.nozominetworks.com/newsroom
A5: Forescout Technologies, Inc. | B5: Jan 16, 2026: Announced CRO promotion (Rob Amezcua) and VP Product Marketing hire (Joe Malenfant). | C5: No recent public activity found | D5: No recent public activity found | E5: https://www.forescout.com/company/newsroom/
A6: Armis, Inc. | B6: Mar 19, 2026: "Armis Launches First-of-Its-Kind Benchmark Report to Warn of Critical Security Gaps in Native AI Development" (Business Wire). Mar 24, 2026: Armis Centrix named "Best Solution" for Cyber Exposure Management at RSAC 2026 (Business Wire). | C6: No recent public activity found | D6: No recent public activity found | E6: https://www.armis.com/newsroom/
A8: Podcast/webcast appearances and upcoming events columns show "No recent public activity found" for all five companies -- this reflects the actual result of this research pass, not a shortcut. This tab is inherently uneven across companies; some will have a rich public footprint, many will have little to nothing findable, and that's expected.

Sheet Notes & Assumptions
A1: Notes & Assumptions
A3: WHAT THIS FILE IS
A4: A sample output demonstrating the structure and formatting the Target Company Research Prompt Builder tool's generated prompt asks Claude to produce. It uses REAL, web-search-verified facts about five well-known OT/ICS cybersecurity vendors (Dragos, Claroty, Nozomi Networks, Forescout, Armis) as of July 2026 -- company size, funding, ownership, and news items are genuine and sourced, not fabricated placeholder data.
A6: WHAT IS ILLUSTRATIVE (NOT A REAL COMPLETED ENGAGEMENT)
A7: Subjective/judgment columns -- Opportunity Fit, Opportunity Relevance, Category, Why This Fits, Executive Role Fit, Warm Introduction Path, and the resulting Suggested Priority Rank -- are illustrative example ratings built around a plausible demo purpose: "prospective clients for a marketing consulting firm serving OT/ICS security vendors." These are demonstration judgment calls to show the tracker's format, not a real completed research engagement.
A9: VERIFIED vs. ESTIMATED
A10: - Company size, HQ location, founding year, ownership/M&A status: verified via multiple independent third-party sources (PitchBook, Tracxn, LeadIQ, company newsrooms, and -- for the Armis/ServiceNow deal specifically -- ServiceNow's own SEC Form 10-Q filing).
A11: - Revenue figures: third-party estimates where a company is privately held and does not disclose financials publicly; noted as estimates in each cell.
A12: - "Recent Hiring Trends" is marked "Not verified in this pass" for all five companies -- a real run of this prompt would check each company's current job postings live at the time of the request, which requires an active search at that moment rather than a one-time snapshot.
A13: - Compensation Benchmark and 10-K-sourced named-executive columns are marked N/A for all five companies because all five are privately held or (Armis, post-acquisition) no longer separately SEC-reporting -- none currently file a 10-K or proxy statement in their own right.
A15: COLOR LEGEND (rating columns: Growth/Revenue Signal, Hiring Signal, Opportunity Relevance, Opportunity Fit)
A16: Very High = darker green | High = green | Medium-High = yellow-green | Medium = yellow | Low-Medium = orange | Low = red
... A22: This sample does not apply the optional company-size or location-radius filters available in the Prompt Builder tool -- all five companies here are well-known, easily verifiable OT/ICS security vendors chosen specifically so every fact in this file could be checked against multiple public sources, rather than being constrained to a specific geography that might force reliance on harder-to-verify smaller/regional companies for a demonstration file.

Sheet Summary
A1: Summary
A3: Total companies researched: | B3: =COUNTA('Company Tracker'!A2:A6) -> 5
A5: Companies by Opportunity Fit
A6: Very High | B6: =COUNTIF('Company Tracker'!O2:O6,A6) -> 1
A7: High | B7: =COUNTIF('Company Tracker'!O2:O6,A7) -> 1
A8: Medium-High | B8: =COUNTIF('Company Tracker'!O2:O6,A8) -> 0
A9: Medium | B9: =COUNTIF('Company Tracker'!O2:O6,A9) -> 3
A10: Low-Medium | B10: =COUNTIF('Company Tracker'!O2:O6,A10) -> 0
A11: Low | B11: =COUNTIF('Company Tracker'!O2:O6,A11) -> 0
A13: Companies by NAICS Code Type
A14: Primary | B14: =COUNTIF('Company Tracker'!F2:F6,A14) -> 5
A15: Secondary | B15: =COUNTIF('Company Tracker'!F2:F6,A15) -> 0
A17: Companies by Category
A18: Actively Expanding / M&A Integration | B18: =COUNTIF('Company Tracker'!P2:P6,A18) -> 1
A19: Actively Expanding / Recently Funded | B19: =COUNTIF('Company Tracker'!P2:P6,A19) -> 1
A20: Established / Leadership Refresh | B20: =COUNTIF('Company Tracker'!P2:P6,A20) -> 1
A21: Recently Acquired / Integration Phase | B21: =COUNTIF('Company Tracker'!P2:P6,A21) -> 2
A24: Top 5 by Suggested Priority Rank
A25: Company | B25: Suggested Priority Rank
A26: =IFERROR(INDEX('Company Tracker'!$A$2:$A$6,MATCH(B26,'Company Tracker'!$AA$2:$AA$6,0)),"") -> Claroty Ltd. | B26: =IFERROR(LARGE('Company Tracker'!$AA$2:$AA$6,1),"") -> 22
A27: =IFERROR(INDEX('Company Tracker'!$A$2:$A$6,MATCH(B27,'Company Tracker'!$AA$2:$AA$6,0)),"") -> Dragos, Inc. | B27: =IFERROR(LARGE('Company Tracker'!$AA$2:$AA$6,2),"") -> 19.5
A28: =IFERROR(INDEX('Company Tracker'!$A$2:$A$6,MATCH(B28,'Company Tracker'!$AA$2:$AA$6,0)),"") -> Armis, Inc. | B28: =IFERROR(LARGE('Company Tracker'!$AA$2:$AA$6,3),"") -> 16
A29: =IFERROR(INDEX('Company Tracker'!$A$2:$A$6,MATCH(B29,'Company Tracker'!$AA$2:$AA$6,0)),"") -> Nozomi Networks | B29: =IFERROR(LARGE('Company Tracker'!$AA$2:$AA$6,4),"") -> 15.3
A30: =IFERROR(INDEX('Company Tracker'!$A$2:$A$6,MATCH(B30,'Company Tracker'!$AA$2:$AA$6,0)),"") -> Forescout Technologies, Inc. | B30: =IFERROR(LARGE('Company Tracker'!$AA$2:$AA$6,5),"") -> 15
